eipiphany_core/__init__.py
eipiphany_core/framework/__init__.py
eipiphany_core/framework/base/__init__.py
eipiphany_core/framework/base/aggregation_strategy.py
eipiphany_core/framework/base/aggregator.py
eipiphany_core/framework/base/dead_letter_channel.py
eipiphany_core/framework/base/default_eip_context_termination.py
eipiphany_core/framework/base/default_error_handler.py
eipiphany_core/framework/base/eip_context.py
eipiphany_core/framework/base/eip_context_termination.py
eipiphany_core/framework/base/endpoint.py
eipiphany_core/framework/base/error_handler.py
eipiphany_core/framework/base/exchange_producer.py
eipiphany_core/framework/base/expression.py
eipiphany_core/framework/base/filter.py
eipiphany_core/framework/base/predicate.py
eipiphany_core/framework/base/processor.py
eipiphany_core/framework/base/route_builder.py
eipiphany_core/framework/base/source.py
eipiphany_core/framework/internal/__init__.py
eipiphany_core/framework/internal/exchange_handler.py
eipiphany_core/framework/internal/process_wrapper.py
eipiphany_core/framework/internal/route.py
eipiphany_core/framework/internal/source_wrapper.py
eipiphany_core/framework/test_support/__init__.py
eipiphany_core/framework/test_support/eip_test_context.py
eipiphany_core/framework/test_support/mock_endpoint.py
eipiphany_core/framework/test_support/test_eip_context_termination.py
eipiphany_core/message/__init__.py
eipiphany_core/message/exchange.py
eipiphany_core-0.1.0.dev20230306154257.dist-info/METADATA
eipiphany_core-0.1.0.dev20230306154257.dist-info/WHEEL
eipiphany_core-0.1.0.dev20230306154257.dist-info/top_level.txt
eipiphany_core-0.1.0.dev20230306154257.dist-info/RECORD
