Metadata-Version: 2.1
Name: eipiphany-core
Version: 0.1.0.dev20230306154257
Summary: Simple Multiprocessing EIP Framework For Python: Core
Home-page: https://github.com/ci-cmg/eipiphany
Classifier: Programming Language :: Python :: 3
Classifier: License :: OSI Approved :: MIT License
Classifier: Operating System :: OS Independent
Requires-Python: >=3.9
